[
  {
    "k": "inject_Journeys",
    "route": "/journeys",
    "blockedRequests": 2,
    "reloadsUsed": 2,
    "cardVisible": true,
    "btnVisible": true,
    "chromeAlive": true,
    "cardGone": true,
    "recoveredH1": "Learning Journeys",
    "finalUrl": "http://localhost:5000/journeys"
  },
  {
    "k": "inject_Search",
    "route": "/search",
    "blockedRequests": 2,
    "reloadsUsed": 2,
    "cardVisible": true,
    "btnVisible": true,
    "chromeAlive": true,
    "cardGone": true,
    "recoveredH1": "Search",
    "finalUrl": "http://localhost:5000/search"
  },
  {
    "k": "inject_About",
    "route": "/about",
    "blockedRequests": 2,
    "reloadsUsed": 2,
    "cardVisible": true,
    "btnVisible": true,
    "chromeAlive": true,
    "cardGone": true,
    "recoveredH1": "About",
    "finalUrl": "http://localhost:5000/about"
  }
]